gmssl_pyx/__init__.py
gmssl_pyx/_version.py
gmssl_pyx/gmsslext.cp38-win_amd64.pyd
gmssl_pyx/gmsslext.pyi
gmssl_pyx/sm2_utils.py
gmssl_pyx-2.0.0.dist-info/LICENSE
gmssl_pyx-2.0.0.dist-info/METADATA
gmssl_pyx-2.0.0.dist-info/WHEEL
gmssl_pyx-2.0.0.dist-info/top_level.txt
gmssl_pyx-2.0.0.dist-info/RECORD
